CHANGES
LICENSE
README.txt
TODO.txt
bootstrap.py
buildout.cfg
setup.cfg
setup.py
iw/__init__.py
iw.releaser.egg-info/PKG-INFO
iw.releaser.egg-info/SOURCES.txt
iw.releaser.egg-info/dependency_links.txt
iw.releaser.egg-info/entry_points.txt
iw.releaser.egg-info/namespace_packages.txt
iw.releaser.egg-info/not-zip-safe
iw.releaser.egg-info/requires.txt
iw.releaser.egg-info/top_level.txt
iw/releaser/README.txt
iw/releaser/__init__.py
iw/releaser/base.py
iw/releaser/bootstrap.py
iw/releaser/commands.py
iw/releaser/config.py
iw/releaser/hook.py
iw/releaser/msgfmt.py
iw/releaser/packet.py
iw/releaser/project.py
iw/releaser/templates.py
iw/releaser/testing.py
iw/releaser/virtualenv.py
iw/releaser/docs/README.txt
iw/releaser/doctests/README.txt
iw/releaser/doctests/build_mo.txt
iw/releaser/doctests/deploy.txt
iw/releaser/doctests/packet.txt
iw/releaser/doctests/project.txt
iw/releaser/doctests/releasing.txt
iw/releaser/templates/iw_plone_project/backups/README.txt
iw/releaser/templates/iw_plone_project/buildout/README.txt_tmpl
iw/releaser/templates/iw_plone_project/buildout/bootstrap.py
iw/releaser/templates/iw_plone_project/buildout/buildout.cfg_tmpl
iw/releaser/templates/iw_plone_project/buildout/ingeniweb.cfg_tmpl
iw/releaser/templates/iw_plone_project/buildout/linux.cfg_tmpl
iw/releaser/templates/iw_plone_project/buildout/plone.cfg_tmpl
iw/releaser/templates/iw_plone_project/buildout/project.cfg_tmpl
iw/releaser/templates/iw_plone_project/buildout/win32.cfg_tmpl
iw/releaser/templates/iw_plone_project/buildout/bin/buildout.bat
iw/releaser/templates/iw_plone_project/buildout/downloads/README.txt
iw/releaser/templates/iw_plone_project/bundles/dev/EXTERNALS.txt_tmpl
iw/releaser/templates/iw_plone_project/docs/README.txt
iw/releaser/templates/iw_plone_project/packages/README.txt
iw/releaser/templates/iw_plone_project/releases/README.txt
iw/releaser/tests/__init__.py
iw/releaser/tests/test_base.py
iw/releaser/tests/test_project.py
iw/releaser/tests/test_releaserdocs.py
iw/releaser/tests/test_releaserdocstrings.py
iw/releaser/tests/buildout/another.cfg
iw/releaser/tests/buildout/buildout.cfg
iw/releaser/tests/data/__init__.py
iw/releaser/tests/data/buildout/README.txt
iw/releaser/tests/data/buildout/__init__.py
iw/releaser/tests/data/buildout/bootstrap.py
