Metadata-Version: 1.0
Name: iw.releaser
Version: 0.4.1
Summary: Setuptools extension to release an egg
Home-page: https://ingeniweb.svn.sourceforge.net/svnroot/ingeniweb/iw.releaser
Author: Ingeniweb
Author-email: support@ingeniweb.com
License: GPL
Keywords: egg setuptools extension
Platform: UNKNOWN
Classifier: Programming Language :: Python
Classifier: Topic :: Software Development :: Libraries :: Python Modules
